niimetric/__init__.py
niimetric/cli.py
niimetric/cropping.py
niimetric/metrics.py
niimetric/utils.py
niimetric-0.1.0.dist-info/licenses/LICENSE
niimetric-0.1.0.dist-info/METADATA
niimetric-0.1.0.dist-info/WHEEL
niimetric-0.1.0.dist-info/entry_points.txt
niimetric-0.1.0.dist-info/top_level.txt
niimetric-0.1.0.dist-info/RECORD
